qsharp/chemistry/__init__.py
qsharp/chemistry/version.py
qsharp/tests/__init__.py
qsharp/tests/test_chemistry.py
qsharp_chemistry-0.25.218240.dist-info/METADATA
qsharp_chemistry-0.25.218240.dist-info/WHEEL
qsharp_chemistry-0.25.218240.dist-info/top_level.txt
qsharp_chemistry-0.25.218240.dist-info/RECORD
