Metadata-Version: 2.1
Name: qsharp-chemistry
Version: 0.25.218240
Summary: Python chemistry libraries for Q#.
Home-page: https://github.com/microsoft/QuantumLibraries
Author: Microsoft
Author-email: que-contacts@microsoft.com
License: UNKNOWN
Platform: UNKNOWN
Classifier: Programming Language :: Python :: 3
Classifier: License :: OSI Approved :: MIT License
Classifier: Operating System :: OS Independent
Requires-Dist: qsharp-core (==0.25.218240)
